setup.py
Products/__init__.py
Products.AngelPas.egg-info/PKG-INFO
Products.AngelPas.egg-info/SOURCES.txt
Products.AngelPas.egg-info/dependency_links.txt
Products.AngelPas.egg-info/namespace_packages.txt
Products.AngelPas.egg-info/not-zip-safe
Products.AngelPas.egg-info/requires.txt
Products.AngelPas.egg-info/top_level.txt
Products/AngelPas/README.txt
Products/AngelPas/__init__.py
Products/AngelPas/plugin.py
Products/AngelPas/utils.py
Products/AngelPas/version.txt
Products/AngelPas/zmi.py
Products/AngelPas/tests/__init__.py
Products/AngelPas/tests/base.py
Products/AngelPas/tests/base_integration.py
Products/AngelPas/tests/mocks.py
Products/AngelPas/tests/test_errors.py
Products/AngelPas/tests/test_group_enumeration.py
Products/AngelPas/tests/test_group_introspection.py
Products/AngelPas/tests/test_groups_for_principal.py
Products/AngelPas/tests/test_networking.py
Products/AngelPas/tests/test_user_enumeration.py
Products/AngelPas/tests/test_user_properties.py
Products/AngelPas/tests/test_xml.py
Products/AngelPas/tests/xml/001.xml
Products/AngelPas/tests/xml/002.xml
Products/AngelPas/tests/xml/113.xml
Products/AngelPas/tests/xml/TR_200506S1_ALH245_001.xml
Products/AngelPas/www/add.pt
Products/AngelPas/www/config.pt
Products/AngelPas/www/multiplugin.gif