Metadata-Version: 1.0
Name: Products.AngelPas
Version: 1.0b1
Summary: AngelPas lets you treat ANGEL-dwelling classes as Plone groups.
Home-page: http://plone.org/products/angelpas
Author: WebLion Group
Author-email: support@weblion.psu.edu
License: GPL
Keywords: web zope plone authentication pas zope2
Platform: UNKNOWN
Classifier: Development Status :: 4 - Beta
Classifier: Framework :: Plone
Classifier: Framework :: Zope2
Classifier: Intended Audience :: System Administrators
Classifier: Programming Language :: Python
Classifier: Topic :: Security
Classifier: Topic :: Software Development :: Libraries :: Python Modules
Classifier: Topic :: System :: Systems Administration :: Authentication/Directory
